Workbook

Sheet Portfolio Summary
B1: GTRE Asset Management Portfolio — Portfolio Summary
B2: Blue cells = your inputs (change these) Black cells = formulas (do not touch) Green cells = links from other tabs
B4: Underwriting Target
B5: Investor Minimum Blended Levered IRR | C5: 0.12
B7: Deal-by-Deal Summary
B8: Asset | C8: Property Name | D8: Product Type | E8: Purchase Price | F8: Equity Required | G8: Levered IRR | H8: Equity Multiple
B9: Asset 1 | C9: ='Asset 1'!C5 | D9: ='Asset 1'!C6 | E9: ='Asset 1'!C8 | F9: ='Asset 1'!C33 | G9: ='Asset 1'!C44 | H9: ='Asset 1'!C45
B10: Asset 2 | C10: ='Asset 2'!C5 | D10: ='Asset 2'!C6 | E10: ='Asset 2'!C8 | F10: ='Asset 2'!C33 | G10: ='Asset 2'!C44 | H10: ='Asset 2'!C45
B11: Asset 3 | C11: ='Asset 3'!C5 | D11: ='Asset 3'!C6 | E11: ='Asset 3'!C8 | F11: ='Asset 3'!C33 | G11: ='Asset 3'!C44 | H11: ='Asset 3'!C45
B12: Product Type Check | C12: =IF(OR(AND(C9=C10,C9<>""),AND(C9=C11,C9<>""),AND(C10=C11,C10<>"")),"DUPLICATE — FIX","OK, all different")
B14: Consolidated Levered Equity Cash Flow (Portfolio)
B15: Year | D15: 0 | E15: 1 | F15: 2 | G15: 3 | H15: 4 | I15: 5 | J15: 6 | K15: 7 | L15: 8 | M15: 9 | N15: 10
B16: Combined Levered Equity Cash Flow | D16: =SUM('Asset 1'!D41,'Asset 2'!D41,'Asset 3'!D41) | E16: =SUM('Asset 1'!E41,'Asset 2'!E41,'Asset 3'!E41) | F16: =SUM('Asset 1'!F41,'Asset 2'!F41,'Asset 3'!F41) | G16: =SUM('Asset 1'!G41,'Asset 2'!G41,'Asset 3'!G41) | H16: =SUM('Asset 1'!H41,'Asset 2'!H41,'Asset 3'!H41) | I16: =SUM('Asset 1'!I41,'Asset 2'!I41,'Asset 3'!I41) | J16: =SUM('Asset 1'!J41,'Asset 2'!J41,'Asset 3'!J41) | K16: =SUM('Asset 1'!K41,'Asset 2'!K41,'Asset 3'!K41) | ... N16: =SUM('Asset 1'!N41,'Asset 2'!N41,'Asset 3'!N41)
B18: Blended Portfolio Returns
B19: Blended Levered IRR | C19: =IRR(D16:N16)
B20: Note: this blends the three levered cash flow streams, then runs one IRR — it is NOT the average of the three deal IRRs above.
B21: Clears 12% Hurdle? | C21: =IF(C19>=C5,"PASS","FAIL — defend the weaker deal's role in the portfolio")
B23: Portfolio Memo
B24: Why these three assets together (income, risk, and return balance across the hold — can instead live in your deck):
B25: [Write your portfolio memo here, or reference the corresponding section of your deck]

Sheet Asset 1
B1: GTRE Asset Management Portfolio — Asset 1
B2: Blue cells = your inputs (change these) Black cells = formulas (do not touch) Green cells = links from other tabs
B4: ① Property Overview
B5: Property Name | C5: [Enter Property 1 Name]
B6: Product Type | C6: [Select Product Type]
B7: Submarket / Location | C7: [Enter Submarket]
B8: Purchase Price
B9: Purchase Date
B10: Hold Period (Years)
B11: Exit Cap Rate
B12: Disposition Cost %
B14: ② In-Place Operations
B15: In-Place NOI (Year 1)
B16: NOI Growth Rate (Yr 2+)
B17: Stabilized Occupancy
B19: ③ Lease Rollover Risk (during hold)
B20: Rollover Event | C20: Year of Event | D20: Downtime Drag (% of NOI, that yr) | E20: Re-Leasing Capex ($) | F20: Mark-to-Market NOI Impact (%)
B21: Event 1
B22: Event 2
B23: Event 3
B26: ④ Acquisition Financing
B27: Loan-to-Value (LTV)
B28: Interest Rate
B29: Interest-Only Period (Yrs)
B30: Amortization Period (Yrs)
B31: Origination Fee %
B32: Loan Amount | C32: =C8*C27
B33: Equity Required | C33: =(C8-C32)+(C32*C31)
B35: ⑤ Annual Levered Cash Flow
B36: Year | D36: 0 | E36: 1 | F36: 2 | G36: 3 | H36: 4 | I36: 5 | J36: 6 | K36: 7 | L36: 8 | M36: 9 | N36: 10
B37: Net Operating Income | E37: =IF($C$10>=1,$C$15,"") | F37: =IF($C$10>=2,E37*(1+$C$16)*IF($C$21=2,(1-$D$21)*(1+$F$21),1)*IF($C$22=2,(1-$D$22)*(1+$F$22),1)*IF($C$23=2,(1-$D$23)*(1+$F$23),1),"") | G37: =IF($C$10>=3,F37*(1+$C$16)*IF($C$21=3,(1-$D$21)*(1+$F$21),1)*IF($C$22=3,(1-$D$22)*(1+$F$22),1)*IF($C$23=3,(1-$D$23)*(1+$F$23),1),"") | H37: =IF($C$10>=4,G37*(1+$C$16)*IF($C$21=4,(1-$D$21)*(1+$F$21),1)*IF($C$22=4,(1-$D$22)*(1+$F$22),1)*IF($C$23=4,(1-$D$23)*(1+$F$23),1),"") | I37: =IF($C$10>=5,H37*(1+$C$16)*IF($C$21=5,(1-$D$21)*(1+$F$21),1)*IF($C$22=5,(1-$D$22)*(1+$F$22),1)*IF($C$23=5,(1-$D$23)*(1+$F$23),1),"") | J37: =IF($C$10>=6,I37*(1+$C$16)*IF($C$21=6,(1-$D$21)*(1+$F$21),1)*IF($C$22=6,(1-$D$22)*(1+$F$22),1)*IF($C$23=6,(1-$D$23)*(1+$F$23),1),"") | K37: =IF($C$10>=7,J37*(1+$C$16)*IF($C$21=7,(1-$D$21)*(1+$F$21),1)*IF($C$22=7,(1-$D$22)*(1+$F$22),1)*IF($C$23=7,(1-$D$23)*(1+$F$23),1),"") | L37: =IF($C$10>=8,K37*(1+$C$16)*IF($C$21=8,(1-$D$21)*(1+$F$21),1)*IF($C$22=8,(1-$D$22)*(1+$F$22),1)*IF($C$23=8,(1-$D$23)*(1+$F$23),1),"") | M37: =IF($C$10>=9,L37*(1+$C$16)*IF($C$21=9,(1-$D$21)*(1+$F$21),1)*IF($C$22=9,(1-$D$22)*(1+$F$22),1)*IF($C$23=9,(1-$D$23)*(1+$F$23),1),"") | N37: =IF($C$10>=10,M37*(1+$C$16)*IF($C$21=10,(1-$D$21)*(1+$F$21),1)*IF($C$22=10,(1-$D$22)*(1+$F$22),1)*IF($C$23=10,(1-$D$23)*(1+$F$23),1),"")
B38: Less: Debt Service | E38: =IF($C$10>=1,IF(1<=$C$29,-$C$32*$C$28,PMT($C$28,$C$30,$C$32)),"") | F38: =IF($C$10>=2,IF(2<=$C$29,-$C$32*$C$28,PMT($C$28,$C$30,$C$32)),"") | G38: =IF($C$10>=3,IF(3<=$C$29,-$C$32*$C$28,PMT($C$28,$C$30,$C$32)),"") | H38: =IF($C$10>=4,IF(4<=$C$29,-$C$32*$C$28,PMT($C$28,$C$30,$C$32)),"") | I38: =IF($C$10>=5,IF(5<=$C$29,-$C$32*$C$28,PMT($C$28,$C$30,$C$32)),"") | J38: =IF($C$10>=6,IF(6<=$C$29,-$C$32*$C$28,PMT($C$28,$C$30,$C$32)),"") | K38: =IF($C$10>=7,IF(7<=$C$29,-$C$32*$C$28,PMT($C$28,$C$30,$C$32)),"") | L38: =IF($C$10>=8,IF(8<=$C$29,-$C$32*$C$28,PMT($C$28,$C$30,$C$32)),"") | M38: =IF($C$10>=9,IF(9<=$C$29,-$C$32*$C$28,PMT($C$28,$C$30,$C$32)),"") | N38: =IF($C$10>=10,IF(10<=$C$29,-$C$32*$C$28,PMT($C$28,$C$30,$C$32)),"")
B39: Less: Re-Leasing Capex | E39: =IF($C$10>=1,-(IF($C$21=1,$E$21,0)+IF($C$22=1,$E$22,0)+IF($C$23=1,$E$23,0)),"") | F39: =IF($C$10>=2,-(IF($C$21=2,$E$21,0)+IF($C$22=2,$E$22,0)+IF($C$23=2,$E$23,0)),"") | G39: =IF($C$10>=3,-(IF($C$21=3,$E$21,0)+IF($C$22=3,$E$22,0)+IF($C$23=3,$E$23,0)),"") | H39: =IF($C$10>=4,-(IF($C$21=4,$E$21,0)+IF($C$22=4,$E$22,0)+IF($C$23=4,$E$23,0)),"") | I39: =IF($C$10>=5,-(IF($C$21=5,$E$21,0)+IF($C$22=5,$E$22,0)+IF($C$23=5,$E$23,0)),"") | J39: =IF($C$10>=6,-(IF($C$21=6,$E$21,0)+IF($C$22=6,$E$22,0)+IF($C$23=6,$E$23,0)),"") | K39: =IF($C$10>=7,-(IF($C$21=7,$E$21,0)+IF($C$22=7,$E$22,0)+IF($C$23=7,$E$23,0)),"") | L39: =IF($C$10>=8,-(IF($C$21=8,$E$21,0)+IF($C$22=8,$E$22,0)+IF($C$23=8,$E$23,0)),"") | M39: =IF($C$10>=9,-(IF($C$21=9,$E$21,0)+IF($C$22=9,$E$22,0)+IF($C$23=9,$E$23,0)),"") | N39: =IF($C$10>=10,-(IF($C$21=10,$E$21,0)+IF($C$22=10,$E$22,0)+IF($C$23=10,$E$23,0)),"")
B40: Net Sale Proceeds at Exit | E40: =IF($C$10=1,(INDEX($D$37:$N$37,1,$C$10+2)/$C$11)*(1-$C$12)-(IF(1<=$C$29,$C$32,$C$32*(1-(((1+$C$28)^(1-$C$29)-1)/((1+$C$28)^$C$30-1))))),"") | F40: =IF($C$10=2,(INDEX($D$37:$N$37,1,$C$10+2)/$C$11)*(1-$C$12)-(IF(2<=$C$29,$C$32,$C$32*(1-(((1+$C$28)^(2-$C$29)-1)/((1+$C$28)^$C$30-1))))),"") | G40: =IF($C$10=3,(INDEX($D$37:$N$37,1,$C$10+2)/$C$11)*(1-$C$12)-(IF(3<=$C$29,$C$32,$C$32*(1-(((1+$C$28)^(3-$C$29)-1)/((1+$C$28)^$C$30-1))))),"") | H40: =IF($C$10=4,(INDEX($D$37:$N$37,1,$C$10+2)/$C$11)*(1-$C$12)-(IF(4<=$C$29,$C$32,$C$32*(1-(((1+$C$28)^(4-$C$29)-1)/((1+$C$28)^$C$30-1))))),"") | I40: =IF($C$10=5,(INDEX($D$37:$N$37,1,$C$10+2)/$C$11)*(1-$C$12)-(IF(5<=$C$29,$C$32,$C$32*(1-(((1+$C$28)^(5-$C$29)-1)/((1+$C$28)^$C$30-1))))),"") | J40: =IF($C$10=6,(INDEX($D$37:$N$37,1,$C$10+2)/$C$11)*(1-$C$12)-(IF(6<=$C$29,$C$32,$C$32*(1-(((1+$C$28)^(6-$C$29)-1)/((1+$C$28)^$C$30-1))))),"") | K40: =IF($C$10=7,(INDEX($D$37:$N$37,1,$C$10+2)/$C$11)*(1-$C$12)-(IF(7<=$C$29,$C$32,$C$32*(1-(((1+$C$28)^(7-$C$29)-1)/((1+$C$28)^$C$30-1))))),"") | L40: =IF($C$10=8,(INDEX($D$37:$N$37,1,$C$10+2)/$C$11)*(1-$C$12)-(IF(8<=$C$29,$C$32,$C$32*(1-(((1+$C$28)^(8-$C$29)-1)/((1+$C$28)^$C$30-1))))),"") | M40: =IF($C$10=9,(INDEX($D$37:$N$37,1,$C$10+2)/$C$11)*(1-$C$12)-(IF(9<=$C$29,$C$32,$C$32*(1-(((1+$C$28)^(9-$C$29)-1)/((1+$C$28)^$C$30-1))))),"") | N40: =IF($C$10=10,(N37*(1+$C$16)/$C$11)*(1-$C$12)-(IF(10<=$C$29,$C$32,$C$32*(1-(((1+$C$28)^(10-$C$29)-1)/((1+$C$28)^$C$30-1))))),"")
B41: Total Levered Equity Cash Flow | D41: =-C33 | E41: =IF($C$10>=1,SUM(E37,E38,E39,E40),"") | F41: =IF($C$10>=2,SUM(F37,F38,F39,F40),"") | G41: =IF($C$10>=3,SUM(G37,G38,G39,G40),"") | H41: =IF($C$10>=4,SUM(H37,H38,H39,H40),"") | I41: =IF($C$10>=5,SUM(I37,I38,I39,I40),"") | J41: =IF($C$10>=6,SUM(J37,J38,J39,J40),"") | K41: =IF($C$10>=7,SUM(K37,K38,K39,K40),"") | L41: =IF($C$10>=8,SUM(L37,L38,L39,L40),"") | M41: =IF($C$10>=9,SUM(M37,M38,M39,M40),"") | N41: =IF($C$10>=10,SUM(N37,N38,N39,N40),"")
B43: ⑥ Returns
B44: Levered IRR | C44: =IRR(D41:N41)
B45: Equity Multiple | C45: =SUMIF(D41:N41,">0")/-D41

Sheet Asset 2
B1: GTRE Asset Management Portfolio — Asset 2
B2: Blue cells = your inputs (change these) Black cells = formulas (do not touch) Green cells = links from other tabs
B4: ① Property Overview
B5: Property Name | C5: [Enter Property 2 Name]
B6: Product Type | C6: [Select Product Type]
B7: Submarket / Location | C7: [Enter Submarket]
B8: Purchase Price
B9: Purchase Date
B10: Hold Period (Years)
B11: Exit Cap Rate
B12: Disposition Cost %
B14: ② In-Place Operations
B15: In-Place NOI (Year 1)
B16: NOI Growth Rate (Yr 2+)
B17: Stabilized Occupancy
B19: ③ Lease Rollover Risk (during hold)
B20: Rollover Event | C20: Year of Event | D20: Downtime Drag (% of NOI, that yr) | E20: Re-Leasing Capex ($) | F20: Mark-to-Market NOI Impact (%)
B21: Event 1
B22: Event 2
B23: Event 3
B26: ④ Acquisition Financing
B27: Loan-to-Value (LTV)
B28: Interest Rate
B29: Interest-Only Period (Yrs)
B30: Amortization Period (Yrs)
B31: Origination Fee %
B32: Loan Amount | C32: =C8*C27
B33: Equity Required | C33: =(C8-C32)+(C32*C31)
B35: ⑤ Annual Levered Cash Flow
B36: Year | D36: 0 | E36: 1 | F36: 2 | G36: 3 | H36: 4 | I36: 5 | J36: 6 | K36: 7 | L36: 8 | M36: 9 | N36: 10
B37: Net Operating Income | E37: =IF($C$10>=1,$C$15,"") | F37: =IF($C$10>=2,E37*(1+$C$16)*IF($C$21=2,(1-$D$21)*(1+$F$21),1)*IF($C$22=2,(1-$D$22)*(1+$F$22),1)*IF($C$23=2,(1-$D$23)*(1+$F$23),1),"") | G37: =IF($C$10>=3,F37*(1+$C$16)*IF($C$21=3,(1-$D$21)*(1+$F$21),1)*IF($C$22=3,(1-$D$22)*(1+$F$22),1)*IF($C$23=3,(1-$D$23)*(1+$F$23),1),"") | H37: =IF($C$10>=4,G37*(1+$C$16)*IF($C$21=4,(1-$D$21)*(1+$F$21),1)*IF($C$22=4,(1-$D$22)*(1+$F$22),1)*IF($C$23=4,(1-$D$23)*(1+$F$23),1),"") | I37: =IF($C$10>=5,H37*(1+$C$16)*IF($C$21=5,(1-$D$21)*(1+$F$21),1)*IF($C$22=5,(1-$D$22)*(1+$F$22),1)*IF($C$23=5,(1-$D$23)*(1+$F$23),1),"") | J37: =IF($C$10>=6,I37*(1+$C$16)*IF($C$21=6,(1-$D$21)*(1+$F$21),1)*IF($C$22=6,(1-$D$22)*(1+$F$22),1)*IF($C$23=6,(1-$D$23)*(1+$F$23),1),"") | K37: =IF($C$10>=7,J37*(1+$C$16)*IF($C$21=7,(1-$D$21)*(1+$F$21),1)*IF($C$22=7,(1-$D$22)*(1+$F$22),1)*IF($C$23=7,(1-$D$23)*(1+$F$23),1),"") | L37: =IF($C$10>=8,K37*(1+$C$16)*IF($C$21=8,(1-$D$21)*(1+$F$21),1)*IF($C$22=8,(1-$D$22)*(1+$F$22),1)*IF($C$23=8,(1-$D$23)*(1+$F$23),1),"") | M37: =IF($C$10>=9,L37*(1+$C$16)*IF($C$21=9,(1-$D$21)*(1+$F$21),1)*IF($C$22=9,(1-$D$22)*(1+$F$22),1)*IF($C$23=9,(1-$D$23)*(1+$F$23),1),"") | N37: =IF($C$10>=10,M37*(1+$C$16)*IF($C$21=10,(1-$D$21)*(1+$F$21),1)*IF($C$22=10,(1-$D$22)*(1+$F$22),1)*IF($C$23=10,(1-$D$23)*(1+$F$23),1),"")
B38: Less: Debt Service | E38: =IF($C$10>=1,IF(1<=$C$29,-$C$32*$C$28,PMT($C$28,$C$30,$C$32)),"") | F38: =IF($C$10>=2,IF(2<=$C$29,-$C$32*$C$28,PMT($C$28,$C$30,$C$32)),"") | G38: =IF($C$10>=3,IF(3<=$C$29,-$C$32*$C$28,PMT($C$28,$C$30,$C$32)),"") | H38: =IF($C$10>=4,IF(4<=$C$29,-$C$32*$C$28,PMT($C$28,$C$30,$C$32)),"") | I38: =IF($C$10>=5,IF(5<=$C$29,-$C$32*$C$28,PMT($C$28,$C$30,$C$32)),"") | J38: =IF($C$10>=6,IF(6<=$C$29,-$C$32*$C$28,PMT($C$28,$C$30,$C$32)),"") | K38: =IF($C$10>=7,IF(7<=$C$29,-$C$32*$C$28,PMT($C$28,$C$30,$C$32)),"") | L38: =IF($C$10>=8,IF(8<=$C$29,-$C$32*$C$28,PMT($C$28,$C$30,$C$32)),"") | M38: =IF($C$10>=9,IF(9<=$C$29,-$C$32*$C$28,PMT($C$28,$C$30,$C$32)),"") | N38: =IF($C$10>=10,IF(10<=$C$29,-$C$32*$C$28,PMT($C$28,$C$30,$C$32)),"")
B39: Less: Re-Leasing Capex | E39: =IF($C$10>=1,-(IF($C$21=1,$E$21,0)+IF($C$22=1,$E$22,0)+IF($C$23=1,$E$23,0)),"") | F39: =IF($C$10>=2,-(IF($C$21=2,$E$21,0)+IF($C$22=2,$E$22,0)+IF($C$23=2,$E$23,0)),"") | G39: =IF($C$10>=3,-(IF($C$21=3,$E$21,0)+IF($C$22=3,$E$22,0)+IF($C$23=3,$E$23,0)),"") | H39: =IF($C$10>=4,-(IF($C$21=4,$E$21,0)+IF($C$22=4,$E$22,0)+IF($C$23=4,$E$23,0)),"") | I39: =IF($C$10>=5,-(IF($C$21=5,$E$21,0)+IF($C$22=5,$E$22,0)+IF($C$23=5,$E$23,0)),"") | J39: =IF($C$10>=6,-(IF($C$21=6,$E$21,0)+IF($C$22=6,$E$22,0)+IF($C$23=6,$E$23,0)),"") | K39: =IF($C$10>=7,-(IF($C$21=7,$E$21,0)+IF($C$22=7,$E$22,0)+IF($C$23=7,$E$23,0)),"") | L39: =IF($C$10>=8,-(IF($C$21=8,$E$21,0)+IF($C$22=8,$E$22,0)+IF($C$23=8,$E$23,0)),"") | M39: =IF($C$10>=9,-(IF($C$21=9,$E$21,0)+IF($C$22=9,$E$22,0)+IF($C$23=9,$E$23,0)),"") | N39: =IF($C$10>=10,-(IF($C$21=10,$E$21,0)+IF($C$22=10,$E$22,0)+IF($C$23=10,$E$23,0)),"")
B40: Net Sale Proceeds at Exit | E40: =IF($C$10=1,(INDEX($D$37:$N$37,1,$C$10+2)/$C$11)*(1-$C$12)-(IF(1<=$C$29,$C$32,$C$32*(1-(((1+$C$28)^(1-$C$29)-1)/((1+$C$28)^$C$30-1))))),"") | F40: =IF($C$10=2,(INDEX($D$37:$N$37,1,$C$10+2)/$C$11)*(1-$C$12)-(IF(2<=$C$29,$C$32,$C$32*(1-(((1+$C$28)^(2-$C$29)-1)/((1+$C$28)^$C$30-1))))),"") | G40: =IF($C$10=3,(INDEX($D$37:$N$37,1,$C$10+2)/$C$11)*(1-$C$12)-(IF(3<=$C$29,$C$32,$C$32*(1-(((1+$C$28)^(3-$C$29)-1)/((1+$C$28)^$C$30-1))))),"") | H40: =IF($C$10=4,(INDEX($D$37:$N$37,1,$C$10+2)/$C$11)*(1-$C$12)-(IF(4<=$C$29,$C$32,$C$32*(1-(((1+$C$28)^(4-$C$29)-1)/((1+$C$28)^$C$30-1))))),"") | I40: =IF($C$10=5,(INDEX($D$37:$N$37,1,$C$10+2)/$C$11)*(1-$C$12)-(IF(5<=$C$29,$C$32,$C$32*(1-(((1+$C$28)^(5-$C$29)-1)/((1+$C$28)^$C$30-1))))),"") | J40: =IF($C$10=6,(INDEX($D$37:$N$37,1,$C$10+2)/$C$11)*(1-$C$12)-(IF(6<=$C$29,$C$32,$C$32*(1-(((1+$C$28)^(6-$C$29)-1)/((1+$C$28)^$C$30-1))))),"") | K40: =IF($C$10=7,(INDEX($D$37:$N$37,1,$C$10+2)/$C$11)*(1-$C$12)-(IF(7<=$C$29,$C$32,$C$32*(1-(((1+$C$28)^(7-$C$29)-1)/((1+$C$28)^$C$30-1))))),"") | L40: =IF($C$10=8,(INDEX($D$37:$N$37,1,$C$10+2)/$C$11)*(1-$C$12)-(IF(8<=$C$29,$C$32,$C$32*(1-(((1+$C$28)^(8-$C$29)-1)/((1+$C$28)^$C$30-1))))),"") | M40: =IF($C$10=9,(INDEX($D$37:$N$37,1,$C$10+2)/$C$11)*(1-$C$12)-(IF(9<=$C$29,$C$32,$C$32*(1-(((1+$C$28)^(9-$C$29)-1)/((1+$C$28)^$C$30-1))))),"") | N40: =IF($C$10=10,(N37*(1+$C$16)/$C$11)*(1-$C$12)-(IF(10<=$C$29,$C$32,$C$32*(1-(((1+$C$28)^(10-$C$29)-1)/((1+$C$28)^$C$30-1))))),"")
B41: Total Levered Equity Cash Flow | D41: =-C33 | E41: =IF($C$10>=1,SUM(E37,E38,E39,E40),"") | F41: =IF($C$10>=2,SUM(F37,F38,F39,F40),"") | G41: =IF($C$10>=3,SUM(G37,G38,G39,G40),"") | H41: =IF($C$10>=4,SUM(H37,H38,H39,H40),"") | I41: =IF($C$10>=5,SUM(I37,I38,I39,I40),"") | J41: =IF($C$10>=6,SUM(J37,J38,J39,J40),"") | K41: =IF($C$10>=7,SUM(K37,K38,K39,K40),"") | L41: =IF($C$10>=8,SUM(L37,L38,L39,L40),"") | M41: =IF($C$10>=9,SUM(M37,M38,M39,M40),"") | N41: =IF($C$10>=10,SUM(N37,N38,N39,N40),"")
B43: ⑥ Returns
B44: Levered IRR | C44: =IRR(D41:N41)
B45: Equity Multiple | C45: =SUMIF(D41:N41,">0")/-D41

Sheet Asset 3
B1: GTRE Asset Management Portfolio — Asset 3
B2: Blue cells = your inputs (change these) Black cells = formulas (do not touch) Green cells = links from other tabs
B4: ① Property Overview
B5: Property Name | C5: [Enter Property 3 Name]
B6: Product Type | C6: [Select Product Type]
B7: Submarket / Location | C7: [Enter Submarket]
B8: Purchase Price
B9: Purchase Date
B10: Hold Period (Years)
B11: Exit Cap Rate
B12: Disposition Cost %
B14: ② In-Place Operations
B15: In-Place NOI (Year 1)
B16: NOI Growth Rate (Yr 2+)
B17: Stabilized Occupancy
B19: ③ Lease Rollover Risk (during hold)
B20: Rollover Event | C20: Year of Event | D20: Downtime Drag (% of NOI, that yr) | E20: Re-Leasing Capex ($) | F20: Mark-to-Market NOI Impact (%)
B21: Event 1
B22: Event 2
B23: Event 3
B26: ④ Acquisition Financing
B27: Loan-to-Value (LTV)
B28: Interest Rate
B29: Interest-Only Period (Yrs)
B30: Amortization Period (Yrs)
B31: Origination Fee %
B32: Loan Amount | C32: =C8*C27
B33: Equity Required | C33: =(C8-C32)+(C32*C31)
B35: ⑤ Annual Levered Cash Flow
B36: Year | D36: 0 | E36: 1 | F36: 2 | G36: 3 | H36: 4 | I36: 5 | J36: 6 | K36: 7 | L36: 8 | M36: 9 | N36: 10
B37: Net Operating Income | E37: =IF($C$10>=1,$C$15,"") | F37: =IF($C$10>=2,E37*(1+$C$16)*IF($C$21=2,(1-$D$21)*(1+$F$21),1)*IF($C$22=2,(1-$D$22)*(1+$F$22),1)*IF($C$23=2,(1-$D$23)*(1+$F$23),1),"") | G37: =IF($C$10>=3,F37*(1+$C$16)*IF($C$21=3,(1-$D$21)*(1+$F$21),1)*IF($C$22=3,(1-$D$22)*(1+$F$22),1)*IF($C$23=3,(1-$D$23)*(1+$F$23),1),"") | H37: =IF($C$10>=4,G37*(1+$C$16)*IF($C$21=4,(1-$D$21)*(1+$F$21),1)*IF($C$22=4,(1-$D$22)*(1+$F$22),1)*IF($C$23=4,(1-$D$23)*(1+$F$23),1),"") | I37: =IF($C$10>=5,H37*(1+$C$16)*IF($C$21=5,(1-$D$21)*(1+$F$21),1)*IF($C$22=5,(1-$D$22)*(1+$F$22),1)*IF($C$23=5,(1-$D$23)*(1+$F$23),1),"") | J37: =IF($C$10>=6,I37*(1+$C$16)*IF($C$21=6,(1-$D$21)*(1+$F$21),1)*IF($C$22=6,(1-$D$22)*(1+$F$22),1)*IF($C$23=6,(1-$D$23)*(1+$F$23),1),"") | K37: =IF($C$10>=7,J37*(1+$C$16)*IF($C$21=7,(1-$D$21)*(1+$F$21),1)*IF($C$22=7,(1-$D$22)*(1+$F$22),1)*IF($C$23=7,(1-$D$23)*(1+$F$23),1),"") | L37: =IF($C$10>=8,K37*(1+$C$16)*IF($C$21=8,(1-$D$21)*(1+$F$21),1)*IF($C$22=8,(1-$D$22)*(1+$F$22),1)*IF($C$23=8,(1-$D$23)*(1+$F$23),1),"") | M37: =IF($C$10>=9,L37*(1+$C$16)*IF($C$21=9,(1-$D$21)*(1+$F$21),1)*IF($C$22=9,(1-$D$22)*(1+$F$22),1)*IF($C$23=9,(1-$D$23)*(1+$F$23),1),"") | N37: =IF($C$10>=10,M37*(1+$C$16)*IF($C$21=10,(1-$D$21)*(1+$F$21),1)*IF($C$22=10,(1-$D$22)*(1+$F$22),1)*IF($C$23=10,(1-$D$23)*(1+$F$23),1),"")
B38: Less: Debt Service | E38: =IF($C$10>=1,IF(1<=$C$29,-$C$32*$C$28,PMT($C$28,$C$30,$C$32)),"") | F38: =IF($C$10>=2,IF(2<=$C$29,-$C$32*$C$28,PMT($C$28,$C$30,$C$32)),"") | G38: =IF($C$10>=3,IF(3<=$C$29,-$C$32*$C$28,PMT($C$28,$C$30,$C$32)),"") | H38: =IF($C$10>=4,IF(4<=$C$29,-$C$32*$C$28,PMT($C$28,$C$30,$C$32)),"") | I38: =IF($C$10>=5,IF(5<=$C$29,-$C$32*$C$28,PMT($C$28,$C$30,$C$32)),"") | J38: =IF($C$10>=6,IF(6<=$C$29,-$C$32*$C$28,PMT($C$28,$C$30,$C$32)),"") | K38: =IF($C$10>=7,IF(7<=$C$29,-$C$32*$C$28,PMT($C$28,$C$30,$C$32)),"") | L38: =IF($C$10>=8,IF(8<=$C$29,-$C$32*$C$28,PMT($C$28,$C$30,$C$32)),"") | M38: =IF($C$10>=9,IF(9<=$C$29,-$C$32*$C$28,PMT($C$28,$C$30,$C$32)),"") | N38: =IF($C$10>=10,IF(10<=$C$29,-$C$32*$C$28,PMT($C$28,$C$30,$C$32)),"")
B39: Less: Re-Leasing Capex | E39: =IF($C$10>=1,-(IF($C$21=1,$E$21,0)+IF($C$22=1,$E$22,0)+IF($C$23=1,$E$23,0)),"") | F39: =IF($C$10>=2,-(IF($C$21=2,$E$21,0)+IF($C$22=2,$E$22,0)+IF($C$23=2,$E$23,0)),"") | G39: =IF($C$10>=3,-(IF($C$21=3,$E$21,0)+IF($C$22=3,$E$22,0)+IF($C$23=3,$E$23,0)),"") | H39: =IF($C$10>=4,-(IF($C$21=4,$E$21,0)+IF($C$22=4,$E$22,0)+IF($C$23=4,$E$23,0)),"") | I39: =IF($C$10>=5,-(IF($C$21=5,$E$21,0)+IF($C$22=5,$E$22,0)+IF($C$23=5,$E$23,0)),"") | J39: =IF($C$10>=6,-(IF($C$21=6,$E$21,0)+IF($C$22=6,$E$22,0)+IF($C$23=6,$E$23,0)),"") | K39: =IF($C$10>=7,-(IF($C$21=7,$E$21,0)+IF($C$22=7,$E$22,0)+IF($C$23=7,$E$23,0)),"") | L39: =IF($C$10>=8,-(IF($C$21=8,$E$21,0)+IF($C$22=8,$E$22,0)+IF($C$23=8,$E$23,0)),"") | M39: =IF($C$10>=9,-(IF($C$21=9,$E$21,0)+IF($C$22=9,$E$22,0)+IF($C$23=9,$E$23,0)),"") | N39: =IF($C$10>=10,-(IF($C$21=10,$E$21,0)+IF($C$22=10,$E$22,0)+IF($C$23=10,$E$23,0)),"")
B40: Net Sale Proceeds at Exit | E40: =IF($C$10=1,(INDEX($D$37:$N$37,1,$C$10+2)/$C$11)*(1-$C$12)-(IF(1<=$C$29,$C$32,$C$32*(1-(((1+$C$28)^(1-$C$29)-1)/((1+$C$28)^$C$30-1))))),"") | F40: =IF($C$10=2,(INDEX($D$37:$N$37,1,$C$10+2)/$C$11)*(1-$C$12)-(IF(2<=$C$29,$C$32,$C$32*(1-(((1+$C$28)^(2-$C$29)-1)/((1+$C$28)^$C$30-1))))),"") | G40: =IF($C$10=3,(INDEX($D$37:$N$37,1,$C$10+2)/$C$11)*(1-$C$12)-(IF(3<=$C$29,$C$32,$C$32*(1-(((1+$C$28)^(3-$C$29)-1)/((1+$C$28)^$C$30-1))))),"") | H40: =IF($C$10=4,(INDEX($D$37:$N$37,1,$C$10+2)/$C$11)*(1-$C$12)-(IF(4<=$C$29,$C$32,$C$32*(1-(((1+$C$28)^(4-$C$29)-1)/((1+$C$28)^$C$30-1))))),"") | I40: =IF($C$10=5,(INDEX($D$37:$N$37,1,$C$10+2)/$C$11)*(1-$C$12)-(IF(5<=$C$29,$C$32,$C$32*(1-(((1+$C$28)^(5-$C$29)-1)/((1+$C$28)^$C$30-1))))),"") | J40: =IF($C$10=6,(INDEX($D$37:$N$37,1,$C$10+2)/$C$11)*(1-$C$12)-(IF(6<=$C$29,$C$32,$C$32*(1-(((1+$C$28)^(6-$C$29)-1)/((1+$C$28)^$C$30-1))))),"") | K40: =IF($C$10=7,(INDEX($D$37:$N$37,1,$C$10+2)/$C$11)*(1-$C$12)-(IF(7<=$C$29,$C$32,$C$32*(1-(((1+$C$28)^(7-$C$29)-1)/((1+$C$28)^$C$30-1))))),"") | L40: =IF($C$10=8,(INDEX($D$37:$N$37,1,$C$10+2)/$C$11)*(1-$C$12)-(IF(8<=$C$29,$C$32,$C$32*(1-(((1+$C$28)^(8-$C$29)-1)/((1+$C$28)^$C$30-1))))),"") | M40: =IF($C$10=9,(INDEX($D$37:$N$37,1,$C$10+2)/$C$11)*(1-$C$12)-(IF(9<=$C$29,$C$32,$C$32*(1-(((1+$C$28)^(9-$C$29)-1)/((1+$C$28)^$C$30-1))))),"") | N40: =IF($C$10=10,(N37*(1+$C$16)/$C$11)*(1-$C$12)-(IF(10<=$C$29,$C$32,$C$32*(1-(((1+$C$28)^(10-$C$29)-1)/((1+$C$28)^$C$30-1))))),"")
B41: Total Levered Equity Cash Flow | D41: =-C33 | E41: =IF($C$10>=1,SUM(E37,E38,E39,E40),"") | F41: =IF($C$10>=2,SUM(F37,F38,F39,F40),"") | G41: =IF($C$10>=3,SUM(G37,G38,G39,G40),"") | H41: =IF($C$10>=4,SUM(H37,H38,H39,H40),"") | I41: =IF($C$10>=5,SUM(I37,I38,I39,I40),"") | J41: =IF($C$10>=6,SUM(J37,J38,J39,J40),"") | K41: =IF($C$10>=7,SUM(K37,K38,K39,K40),"") | L41: =IF($C$10>=8,SUM(L37,L38,L39,L40),"") | M41: =IF($C$10>=9,SUM(M37,M38,M39,M40),"") | N41: =IF($C$10>=10,SUM(N37,N38,N39,N40),"")
B43: ⑥ Returns
B44: Levered IRR | C44: =IRR(D41:N41)
B45: Equity Multiple | C45: =SUMIF(D41:N41,">0")/-D41
