Workbook

Sheet Industrial Underwriting
B1: GTRE Industrial Underwriting Model — Ground-Up Development or Value-Add Acquisition
B2: Blue cells = your inputs (change these) Black cells = formulas (do not touch) Green cells = links from other tabs
B4: ① Property Overview
B5: Property Name | C5: [Enter Property Name]
B6: Deal Type | C6: [Select Deal Type]
B7: Submarket / Location | C7: [Enter Submarket]
B8: Building GSF
B9: Site Acreage
B10: Clear Height (ft)
B11: Land / Acquisition Cost
B12: Closing Date
B13: Hold Period (Years)
B14: Exit Cap Rate
B15: Disposition Cost %
B17: ② Development / Capital Budget
B18: Ground-up: enter full construction hard costs. Value-add: enter your renovation / capex budget here instead. Land / Acquisition Cost above covers either the land price or the purchase price.
B19: Hard Costs ($/SF of GSF)
B20: Total Hard Costs | C20: =C19*C8
B21: Soft Costs (% of Hard Costs)
B22: Total Soft Costs | C22: =C20*C21
B23: Contingency (% of Hard + Soft)
B24: Contingency $ | C24: =(C20+C22)*C23
B25: Total Project Cost | C25: =C11+C20+C22+C24
B27: ③ Tenant Roster (up to 4 tenants — leave rows blank if fewer)
B28: Tenant | C28: SF Leased | D28: Lease Start (Year #) | E28: Lease Term (Yrs) | F28: Base Rent ($/SF/Yr, NNN) | G28: Annual Escalation % | H28: TI Allowance ($/SF) | I28: Free Rent (Months, Yr 1)
B29: Tenant 1
B30: Tenant 2
B31: Tenant 3
B32: Tenant 4
B34: ④ Operations & Reimbursements
B35: Vacancy / Credit Loss %
B36: Non-Reimbursed Opex ($/SF/Yr)
B37: Management Fee (% of EGI)
B38: Expense Growth Rate
B40: ⑤ Construction / Renovation & Lease-Up Timing
B41: Construction / Renovation Duration (Months)
B42: Pre-Leased at Delivery? | C42: [Select]
B43: Months to Full Stabilization (if not pre-leased)
B45: ⑥ Financing
B46: Loan-to-Cost / Loan-to-Value
B47: Interest Rate
B48: Interest-Only Period (Years)
B49: Amortization Period (Years)
B50: Origination Fee %
B51: Loan Amount | C51: =C25*C46
B52: Equity Required | C52: =(C25-C51)+(C51*C50)
B54: ⑦ Annual Cash Flow
B55: Year | D55: 0 | E55: 1 | F55: 2 | G55: 3 | H55: 4 | I55: 5 | J55: 6 | K55: 7 | L55: 8 | M55: 9 | N55: 10
B56: Tenant Rent Buildout
B57: Tenant 1 Rent | D57: 0 | E57: =IF(AND($C$29<>"",1>=$D$29,1<$D$29+$E$29),$C$29*$F$29*(1+$G$29)^(1-$D$29)*IF(1=$D$29,(12-$I$29)/12,1),0) | F57: =IF(AND($C$29<>"",2>=$D$29,2<$D$29+$E$29),$C$29*$F$29*(1+$G$29)^(2-$D$29)*IF(2=$D$29,(12-$I$29)/12,1),0) | G57: =IF(AND($C$29<>"",3>=$D$29,3<$D$29+$E$29),$C$29*$F$29*(1+$G$29)^(3-$D$29)*IF(3=$D$29,(12-$I$29)/12,1),0) | H57: =IF(AND($C$29<>"",4>=$D$29,4<$D$29+$E$29),$C$29*$F$29*(1+$G$29)^(4-$D$29)*IF(4=$D$29,(12-$I$29)/12,1),0) | I57: =IF(AND($C$29<>"",5>=$D$29,5<$D$29+$E$29),$C$29*$F$29*(1+$G$29)^(5-$D$29)*IF(5=$D$29,(12-$I$29)/12,1),0) | J57: =IF(AND($C$29<>"",6>=$D$29,6<$D$29+$E$29),$C$29*$F$29*(1+$G$29)^(6-$D$29)*IF(6=$D$29,(12-$I$29)/12,1),0) | K57: =IF(AND($C$29<>"",7>=$D$29,7<$D$29+$E$29),$C$29*$F$29*(1+$G$29)^(7-$D$29)*IF(7=$D$29,(12-$I$29)/12,1),0) | L57: =IF(AND($C$29<>"",8>=$D$29,8<$D$29+$E$29),$C$29*$F$29*(1+$G$29)^(8-$D$29)*IF(8=$D$29,(12-$I$29)/12,1),0) | M57: =IF(AND($C$29<>"",9>=$D$29,9<$D$29+$E$29),$C$29*$F$29*(1+$G$29)^(9-$D$29)*IF(9=$D$29,(12-$I$29)/12,1),0) | N57: =IF(AND($C$29<>"",10>=$D$29,10<$D$29+$E$29),$C$29*$F$29*(1+$G$29)^(10-$D$29)*IF(10=$D$29,(12-$I$29)/12,1),0)
B58: Tenant 2 Rent | D58: 0 | E58: =IF(AND($C$30<>"",1>=$D$30,1<$D$30+$E$30),$C$30*$F$30*(1+$G$30)^(1-$D$30)*IF(1=$D$30,(12-$I$30)/12,1),0) | F58: =IF(AND($C$30<>"",2>=$D$30,2<$D$30+$E$30),$C$30*$F$30*(1+$G$30)^(2-$D$30)*IF(2=$D$30,(12-$I$30)/12,1),0) | G58: =IF(AND($C$30<>"",3>=$D$30,3<$D$30+$E$30),$C$30*$F$30*(1+$G$30)^(3-$D$30)*IF(3=$D$30,(12-$I$30)/12,1),0) | H58: =IF(AND($C$30<>"",4>=$D$30,4<$D$30+$E$30),$C$30*$F$30*(1+$G$30)^(4-$D$30)*IF(4=$D$30,(12-$I$30)/12,1),0) | I58: =IF(AND($C$30<>"",5>=$D$30,5<$D$30+$E$30),$C$30*$F$30*(1+$G$30)^(5-$D$30)*IF(5=$D$30,(12-$I$30)/12,1),0) | J58: =IF(AND($C$30<>"",6>=$D$30,6<$D$30+$E$30),$C$30*$F$30*(1+$G$30)^(6-$D$30)*IF(6=$D$30,(12-$I$30)/12,1),0) | K58: =IF(AND($C$30<>"",7>=$D$30,7<$D$30+$E$30),$C$30*$F$30*(1+$G$30)^(7-$D$30)*IF(7=$D$30,(12-$I$30)/12,1),0) | L58: =IF(AND($C$30<>"",8>=$D$30,8<$D$30+$E$30),$C$30*$F$30*(1+$G$30)^(8-$D$30)*IF(8=$D$30,(12-$I$30)/12,1),0) | M58: =IF(AND($C$30<>"",9>=$D$30,9<$D$30+$E$30),$C$30*$F$30*(1+$G$30)^(9-$D$30)*IF(9=$D$30,(12-$I$30)/12,1),0) | N58: =IF(AND($C$30<>"",10>=$D$30,10<$D$30+$E$30),$C$30*$F$30*(1+$G$30)^(10-$D$30)*IF(10=$D$30,(12-$I$30)/12,1),0)
B59: Tenant 3 Rent | D59: 0 | E59: =IF(AND($C$31<>"",1>=$D$31,1<$D$31+$E$31),$C$31*$F$31*(1+$G$31)^(1-$D$31)*IF(1=$D$31,(12-$I$31)/12,1),0) | F59: =IF(AND($C$31<>"",2>=$D$31,2<$D$31+$E$31),$C$31*$F$31*(1+$G$31)^(2-$D$31)*IF(2=$D$31,(12-$I$31)/12,1),0) | G59: =IF(AND($C$31<>"",3>=$D$31,3<$D$31+$E$31),$C$31*$F$31*(1+$G$31)^(3-$D$31)*IF(3=$D$31,(12-$I$31)/12,1),0) | H59: =IF(AND($C$31<>"",4>=$D$31,4<$D$31+$E$31),$C$31*$F$31*(1+$G$31)^(4-$D$31)*IF(4=$D$31,(12-$I$31)/12,1),0) | I59: =IF(AND($C$31<>"",5>=$D$31,5<$D$31+$E$31),$C$31*$F$31*(1+$G$31)^(5-$D$31)*IF(5=$D$31,(12-$I$31)/12,1),0) | J59: =IF(AND($C$31<>"",6>=$D$31,6<$D$31+$E$31),$C$31*$F$31*(1+$G$31)^(6-$D$31)*IF(6=$D$31,(12-$I$31)/12,1),0) | K59: =IF(AND($C$31<>"",7>=$D$31,7<$D$31+$E$31),$C$31*$F$31*(1+$G$31)^(7-$D$31)*IF(7=$D$31,(12-$I$31)/12,1),0) | L59: =IF(AND($C$31<>"",8>=$D$31,8<$D$31+$E$31),$C$31*$F$31*(1+$G$31)^(8-$D$31)*IF(8=$D$31,(12-$I$31)/12,1),0) | M59: =IF(AND($C$31<>"",9>=$D$31,9<$D$31+$E$31),$C$31*$F$31*(1+$G$31)^(9-$D$31)*IF(9=$D$31,(12-$I$31)/12,1),0) | N59: =IF(AND($C$31<>"",10>=$D$31,10<$D$31+$E$31),$C$31*$F$31*(1+$G$31)^(10-$D$31)*IF(10=$D$31,(12-$I$31)/12,1),0)
B60: Tenant 4 Rent | D60: 0 | E60: =IF(AND($C$32<>"",1>=$D$32,1<$D$32+$E$32),$C$32*$F$32*(1+$G$32)^(1-$D$32)*IF(1=$D$32,(12-$I$32)/12,1),0) | F60: =IF(AND($C$32<>"",2>=$D$32,2<$D$32+$E$32),$C$32*$F$32*(1+$G$32)^(2-$D$32)*IF(2=$D$32,(12-$I$32)/12,1),0) | G60: =IF(AND($C$32<>"",3>=$D$32,3<$D$32+$E$32),$C$32*$F$32*(1+$G$32)^(3-$D$32)*IF(3=$D$32,(12-$I$32)/12,1),0) | H60: =IF(AND($C$32<>"",4>=$D$32,4<$D$32+$E$32),$C$32*$F$32*(1+$G$32)^(4-$D$32)*IF(4=$D$32,(12-$I$32)/12,1),0) | I60: =IF(AND($C$32<>"",5>=$D$32,5<$D$32+$E$32),$C$32*$F$32*(1+$G$32)^(5-$D$32)*IF(5=$D$32,(12-$I$32)/12,1),0) | J60: =IF(AND($C$32<>"",6>=$D$32,6<$D$32+$E$32),$C$32*$F$32*(1+$G$32)^(6-$D$32)*IF(6=$D$32,(12-$I$32)/12,1),0) | K60: =IF(AND($C$32<>"",7>=$D$32,7<$D$32+$E$32),$C$32*$F$32*(1+$G$32)^(7-$D$32)*IF(7=$D$32,(12-$I$32)/12,1),0) | L60: =IF(AND($C$32<>"",8>=$D$32,8<$D$32+$E$32),$C$32*$F$32*(1+$G$32)^(8-$D$32)*IF(8=$D$32,(12-$I$32)/12,1),0) | M60: =IF(AND($C$32<>"",9>=$D$32,9<$D$32+$E$32),$C$32*$F$32*(1+$G$32)^(9-$D$32)*IF(9=$D$32,(12-$I$32)/12,1),0) | N60: =IF(AND($C$32<>"",10>=$D$32,10<$D$32+$E$32),$C$32*$F$32*(1+$G$32)^(10-$D$32)*IF(10=$D$32,(12-$I$32)/12,1),0)
B61: Less: TI Allowance (paid in lease start year) | D61: 0 | E61: =-(IF($D$29=1,$C$29*$H$29,0)+IF($D$30=1,$C$30*$H$30,0)+IF($D$31=1,$C$31*$H$31,0)+IF($D$32=1,$C$32*$H$32,0)) | F61: =-(IF($D$29=2,$C$29*$H$29,0)+IF($D$30=2,$C$30*$H$30,0)+IF($D$31=2,$C$31*$H$31,0)+IF($D$32=2,$C$32*$H$32,0)) | G61: =-(IF($D$29=3,$C$29*$H$29,0)+IF($D$30=3,$C$30*$H$30,0)+IF($D$31=3,$C$31*$H$31,0)+IF($D$32=3,$C$32*$H$32,0)) | H61: =-(IF($D$29=4,$C$29*$H$29,0)+IF($D$30=4,$C$30*$H$30,0)+IF($D$31=4,$C$31*$H$31,0)+IF($D$32=4,$C$32*$H$32,0)) | I61: =-(IF($D$29=5,$C$29*$H$29,0)+IF($D$30=5,$C$30*$H$30,0)+IF($D$31=5,$C$31*$H$31,0)+IF($D$32=5,$C$32*$H$32,0)) | J61: =-(IF($D$29=6,$C$29*$H$29,0)+IF($D$30=6,$C$30*$H$30,0)+IF($D$31=6,$C$31*$H$31,0)+IF($D$32=6,$C$32*$H$32,0)) | K61: =-(IF($D$29=7,$C$29*$H$29,0)+IF($D$30=7,$C$30*$H$30,0)+IF($D$31=7,$C$31*$H$31,0)+IF($D$32=7,$C$32*$H$32,0)) | L61: =-(IF($D$29=8,$C$29*$H$29,0)+IF($D$30=8,$C$30*$H$30,0)+IF($D$31=8,$C$31*$H$31,0)+IF($D$32=8,$C$32*$H$32,0)) | M61: =-(IF($D$29=9,$C$29*$H$29,0)+IF($D$30=9,$C$30*$H$30,0)+IF($D$31=9,$C$31*$H$31,0)+IF($D$32=9,$C$32*$H$32,0)) | N61: =-(IF($D$29=10,$C$29*$H$29,0)+IF($D$30=10,$C$30*$H$30,0)+IF($D$31=10,$C$31*$H$31,0)+IF($D$32=10,$C$32*$H$32,0))
B63: Gross Potential Rent | D63: 0 | E63: =SUM(E57:E60) | F63: =SUM(F57:F60) | G63: =SUM(G57:G60) | H63: =SUM(H57:H60) | I63: =SUM(I57:I60) | J63: =SUM(J57:J60) | K63: =SUM(K57:K60) | L63: =SUM(L57:L60) | ... N63: =SUM(N57:N60)
B64: Less: Vacancy / Credit Loss | D64: 0 | E64: =-E63*$C$35 | F64: =-F63*$C$35 | G64: =-G63*$C$35 | H64: =-H63*$C$35 | I64: =-I63*$C$35 | J64: =-J63*$C$35 | K64: =-K63*$C$35 | L64: =-L63*$C$35 | ... N64: =-N63*$C$35
B65: Effective Rental Income | D65: 0 | E65: =SUM(E63:E64) | F65: =SUM(F63:F64) | G65: =SUM(G63:G64) | H65: =SUM(H63:H64) | I65: =SUM(I63:I64) | J65: =SUM(J63:J64) | K65: =SUM(K63:K64) | L65: =SUM(L63:L64) | ... N65: =SUM(N63:N64)
B66: Less: Non-Reimbursed Opex | D66: 0 | E66: =-$C$36*$C$8*(1+$C$38)^(1-1) | F66: =-$C$36*$C$8*(1+$C$38)^(2-1) | G66: =-$C$36*$C$8*(1+$C$38)^(3-1) | H66: =-$C$36*$C$8*(1+$C$38)^(4-1) | I66: =-$C$36*$C$8*(1+$C$38)^(5-1) | J66: =-$C$36*$C$8*(1+$C$38)^(6-1) | K66: =-$C$36*$C$8*(1+$C$38)^(7-1) | L66: =-$C$36*$C$8*(1+$C$38)^(8-1) | M66: =-$C$36*$C$8*(1+$C$38)^(9-1) | N66: =-$C$36*$C$8*(1+$C$38)^(10-1)
B67: Less: Management Fee | D67: 0 | E67: =-E65*$C$37 | F67: =-F65*$C$37 | G67: =-G65*$C$37 | H67: =-H65*$C$37 | I67: =-I65*$C$37 | J67: =-J65*$C$37 | K67: =-K65*$C$37 | L67: =-L65*$C$37 | ... N67: =-N65*$C$37
B68: Net Operating Income | D68: 0 | E68: =SUM(E65:E67) | F68: =SUM(F65:F67) | G68: =SUM(G65:G67) | H68: =SUM(H65:H67) | I68: =SUM(I65:I67) | J68: =SUM(J65:J67) | K68: =SUM(K65:K67) | L68: =SUM(L65:L67) | ... N68: =SUM(N65:N67)
B69: Less: Debt Service | E69: =IF($C$13>=1,IF(1<=$C$48,-$C$51*$C$47,PMT($C$47,$C$49,$C$51)),"") | F69: =IF($C$13>=2,IF(2<=$C$48,-$C$51*$C$47,PMT($C$47,$C$49,$C$51)),"") | G69: =IF($C$13>=3,IF(3<=$C$48,-$C$51*$C$47,PMT($C$47,$C$49,$C$51)),"") | H69: =IF($C$13>=4,IF(4<=$C$48,-$C$51*$C$47,PMT($C$47,$C$49,$C$51)),"") | I69: =IF($C$13>=5,IF(5<=$C$48,-$C$51*$C$47,PMT($C$47,$C$49,$C$51)),"") | J69: =IF($C$13>=6,IF(6<=$C$48,-$C$51*$C$47,PMT($C$47,$C$49,$C$51)),"") | K69: =IF($C$13>=7,IF(7<=$C$48,-$C$51*$C$47,PMT($C$47,$C$49,$C$51)),"") | L69: =IF($C$13>=8,IF(8<=$C$48,-$C$51*$C$47,PMT($C$47,$C$49,$C$51)),"") | M69: =IF($C$13>=9,IF(9<=$C$48,-$C$51*$C$47,PMT($C$47,$C$49,$C$51)),"") | N69: =IF($C$13>=10,IF(10<=$C$48,-$C$51*$C$47,PMT($C$47,$C$49,$C$51)),"")
B70: Net Sale Proceeds at Exit | E70: =IF($C$13=1,(INDEX($D$68:$N$68,1,$C$13+2)/$C$14)*(1-$C$15)-(IF(1<=$C$48,$C$51,$C$51*(1-(((1+$C$47)^(1-$C$48)-1)/((1+$C$47)^$C$49-1))))),"") | F70: =IF($C$13=2,(INDEX($D$68:$N$68,1,$C$13+2)/$C$14)*(1-$C$15)-(IF(2<=$C$48,$C$51,$C$51*(1-(((1+$C$47)^(2-$C$48)-1)/((1+$C$47)^$C$49-1))))),"") | G70: =IF($C$13=3,(INDEX($D$68:$N$68,1,$C$13+2)/$C$14)*(1-$C$15)-(IF(3<=$C$48,$C$51,$C$51*(1-(((1+$C$47)^(3-$C$48)-1)/((1+$C$47)^$C$49-1))))),"") | H70: =IF($C$13=4,(INDEX($D$68:$N$68,1,$C$13+2)/$C$14)*(1-$C$15)-(IF(4<=$C$48,$C$51,$C$51*(1-(((1+$C$47)^(4-$C$48)-1)/((1+$C$47)^$C$49-1))))),"") | I70: =IF($C$13=5,(INDEX($D$68:$N$68,1,$C$13+2)/$C$14)*(1-$C$15)-(IF(5<=$C$48,$C$51,$C$51*(1-(((1+$C$47)^(5-$C$48)-1)/((1+$C$47)^$C$49-1))))),"") | J70: =IF($C$13=6,(INDEX($D$68:$N$68,1,$C$13+2)/$C$14)*(1-$C$15)-(IF(6<=$C$48,$C$51,$C$51*(1-(((1+$C$47)^(6-$C$48)-1)/((1+$C$47)^$C$49-1))))),"") | K70: =IF($C$13=7,(INDEX($D$68:$N$68,1,$C$13+2)/$C$14)*(1-$C$15)-(IF(7<=$C$48,$C$51,$C$51*(1-(((1+$C$47)^(7-$C$48)-1)/((1+$C$47)^$C$49-1))))),"") | L70: =IF($C$13=8,(INDEX($D$68:$N$68,1,$C$13+2)/$C$14)*(1-$C$15)-(IF(8<=$C$48,$C$51,$C$51*(1-(((1+$C$47)^(8-$C$48)-1)/((1+$C$47)^$C$49-1))))),"") | M70: =IF($C$13=9,(INDEX($D$68:$N$68,1,$C$13+2)/$C$14)*(1-$C$15)-(IF(9<=$C$48,$C$51,$C$51*(1-(((1+$C$47)^(9-$C$48)-1)/((1+$C$47)^$C$49-1))))),"") | N70: =IF($C$13=10,(N68*(1+$C$38)/$C$14)*(1-$C$15)-(IF(10<=$C$48,$C$51,$C$51*(1-(((1+$C$47)^(10-$C$48)-1)/((1+$C$47)^$C$49-1))))),"")
B71: Total Levered Cash Flow | D71: =-C52 | E71: =IF($C$13>=1,SUM(E68:E70)+E61,"") | F71: =IF($C$13>=2,SUM(F68:F70)+F61,"") | G71: =IF($C$13>=3,SUM(G68:G70)+G61,"") | H71: =IF($C$13>=4,SUM(H68:H70)+H61,"") | I71: =IF($C$13>=5,SUM(I68:I70)+I61,"") | J71: =IF($C$13>=6,SUM(J68:J70)+J61,"") | K71: =IF($C$13>=7,SUM(K68:K70)+K61,"") | L71: =IF($C$13>=8,SUM(L68:L70)+L61,"") | M71: =IF($C$13>=9,SUM(M68:M70)+M61,"") | N71: =IF($C$13>=10,SUM(N68:N70)+N61,"")
B73: Total Unlevered Cash Flow | D73: =-C25 | E73: =IF($C$13>=1,E68+E61+IF($C$13=1,(INDEX($D$68:$N$68,1,$C$13+2)/$C$14)*(1-$C$15),0),"") | F73: =IF($C$13>=2,F68+F61+IF($C$13=2,(INDEX($D$68:$N$68,1,$C$13+2)/$C$14)*(1-$C$15),0),"") | G73: =IF($C$13>=3,G68+G61+IF($C$13=3,(INDEX($D$68:$N$68,1,$C$13+2)/$C$14)*(1-$C$15),0),"") | H73: =IF($C$13>=4,H68+H61+IF($C$13=4,(INDEX($D$68:$N$68,1,$C$13+2)/$C$14)*(1-$C$15),0),"") | I73: =IF($C$13>=5,I68+I61+IF($C$13=5,(INDEX($D$68:$N$68,1,$C$13+2)/$C$14)*(1-$C$15),0),"") | J73: =IF($C$13>=6,J68+J61+IF($C$13=6,(INDEX($D$68:$N$68,1,$C$13+2)/$C$14)*(1-$C$15),0),"") | K73: =IF($C$13>=7,K68+K61+IF($C$13=7,(INDEX($D$68:$N$68,1,$C$13+2)/$C$14)*(1-$C$15),0),"") | L73: =IF($C$13>=8,L68+L61+IF($C$13=8,(INDEX($D$68:$N$68,1,$C$13+2)/$C$14)*(1-$C$15),0),"") | M73: =IF($C$13>=9,M68+M61+IF($C$13=9,(INDEX($D$68:$N$68,1,$C$13+2)/$C$14)*(1-$C$15),0),"") | N73: =IF($C$13=10,N68+N61+IF($C$13=10,(N68*(1+$C$38)/$C$14)*(1-$C$15),0),"")
B75: ⑧ Returns
B76: Stabilized NOI (Year 1) | C76: =E68
B77: Yield on Cost | C77: =C76/C25
B78: Development / Value-Add Spread (vs Exit Cap) | C78: =C77-C14
B79: Levered IRR | C79: =IRR(D71:N71)
B80: Unlevered IRR | C80: =IRR(D73:N73)
B81: Equity Multiple | C81: =SUMIF(D71:N71,">0")/-D71

Sheet Exit Cap Sensitivity
B1: Exit Cap Rate Sensitivity
B2: Shows how sale price and the yield-on-cost-to-cap-rate spread move with the exit cap rate. Base case (column E) links to your assumption on the main tab.
B4: Scenario | C4: -100 bps | D4: -50 bps | E4: Base Case | F4: +50 bps | G4: +100 bps
B5: Exit Cap Rate | C5: ='Industrial Underwriting'!$C$14+(-0.01) | D5: ='Industrial Underwriting'!$C$14+(-0.005) | E5: ='Industrial Underwriting'!$C$14+(0) | F5: ='Industrial Underwriting'!$C$14+(0.005) | G5: ='Industrial Underwriting'!$C$14+(0.01)
B6: Implied Sale Price | C6: =(INDEX('Industrial Underwriting'!$D$68:$N$68,1,'Industrial Underwriting'!$C$13+2)/C5)*(1-'Industrial Underwriting'!$C$15) | D6: =(INDEX('Industrial Underwriting'!$D$68:$N$68,1,'Industrial Underwriting'!$C$13+2)/D5)*(1-'Industrial Underwriting'!$C$15) | E6: =(INDEX('Industrial Underwriting'!$D$68:$N$68,1,'Industrial Underwriting'!$C$13+2)/E5)*(1-'Industrial Underwriting'!$C$15) | F6: =(INDEX('Industrial Underwriting'!$D$68:$N$68,1,'Industrial Underwriting'!$C$13+2)/F5)*(1-'Industrial Underwriting'!$C$15) | G6: =(INDEX('Industrial Underwriting'!$D$68:$N$68,1,'Industrial Underwriting'!$C$13+2)/G5)*(1-'Industrial Underwriting'!$C$15)
B7: Yield-on-Cost vs. Cap Rate Spread | C7: ='Industrial Underwriting'!$C$77-C5 | D7: ='Industrial Underwriting'!$C$77-D5 | E7: ='Industrial Underwriting'!$C$77-E5 | F7: ='Industrial Underwriting'!$C$77-F5 | G7: ='Industrial Underwriting'!$C$77-G5
